main.py
opencontest_client-2.3.0.dist-info/LICENSE
opencontest_client-2.3.0.dist-info/METADATA
opencontest_client-2.3.0.dist-info/WHEEL
opencontest_client-2.3.0.dist-info/entry_points.txt
opencontest_client-2.3.0.dist-info/top_level.txt
opencontest_client-2.3.0.dist-info/RECORD
