Metadata-Version: 2.1
Name: opencontest-client
Version: 2.3.0
Summary: A very simple OpenContest command line client written in Python
Home-page: https://github.com/LadueCS/OpenContest-Client
Author: Anthony Wang
Author-email: ta180m@pm.me
License: UNKNOWN
Platform: UNKNOWN
Classifier: Environment :: Console
Classifier: Intended Audience :: End Users/Desktop
Classifier: Programming Language :: Python :: 3
Classifier: License :: OSI Approved :: GNU General Public License v3 (GPLv3)
Classifier: Operating System :: OS Independent
License-File: LICENSE
Requires-Dist: requests
